main.py
coach/__init__.py
coach/coach.py
coach_cli-1.2.dist-info/LICENSE
coach_cli-1.2.dist-info/METADATA
coach_cli-1.2.dist-info/WHEEL
coach_cli-1.2.dist-info/entry_points.txt
coach_cli-1.2.dist-info/top_level.txt
coach_cli-1.2.dist-info/RECORD
