Metadata-Version: 2.1
Name: coach-cli
Version: 1.2
Summary: CLI Utility for interacting with coach
Home-page: https://coach.lkuich.com
Author: Loren Kuich
Author-email: loren@lkuich.com
License: UNKNOWN
Platform: UNKNOWN
Classifier: Programming Language :: Python :: 3.6
Classifier: Programming Language :: Python :: 3.7
Classifier: License :: OSI Approved :: MIT License
Classifier: Operating System :: OS Independent
Requires-Dist: Click
Requires-Dist: boto3
Requires-Dist: requests
Requires-Dist: coach-ml (==0.22)
